{
  "character": "Dee Jay",
  "entries": [
    {
      "category": "normal",
      "move": "Crouch MP",
      "set": {
        "recovery": "*14"
      }
    },
    {
      "category": "normal",
      "move": "Dee Jay Special 2",
      "set": {
        "recovery": "24",
        "startup": "11"
      }
    },
    {
      "category": "normal",
      "move": "Drive Parry",
      "set": {
        "recovery": "33"
      }
    },
    {
      "category": "normal",
      "move": "Funky Dance 2",
      "set": {
        "recovery": "17",
        "startup": "12"
      }
    },
    {
      "category": "normal",
      "move": "HK Jackknife Maximum",
      "set": {
        "recovery": "17+15 land"
      }
    },
    {
      "category": "normal",
      "move": "HP Air Slasher",
      "set": {
        "startup": "17"
      }
    },
    {
      "category": "normal",
      "move": "Jump HK",
      "set": {
        "recovery": "3 land"
      }
    },
    {
      "category": "normal",
      "move": "Jump HP",
      "set": {
        "recovery": "3 land"
      }
    },
    {
      "category": "normal",
      "move": "Jump LK",
      "set": {
        "recovery": "3 land"
      }
    },
    {
      "category": "normal",
      "move": "Jump LP",
      "set": {
        "recovery": "3 land"
      }
    },
    {
      "category": "normal",
      "move": "Jump MK",
      "set": {
        "recovery": "3 land"
      }
    },
    {
      "category": "normal",
      "move": "Jump MP",
      "set": {
        "recovery": "3 land"
      }
    },
    {
      "category": "normal",
      "move": "Knee Shot",
      "set": {
        "recovery": "3 land"
      }
    },
    {
      "category": "normal",
      "move": "LK Jackknife Maximum",
      "set": {
        "recovery": "6 land"
      }
    },
    {
      "category": "normal",
      "move": "MK Jackknife Maximum",
      "set": {
        "recovery": "22+10 land"
      }
    },
    {
      "category": "normal",
      "move": "OD Air Slasher",
      "set": {
        "startup": "10"
      }
    },
    {
      "category": "normal",
      "move": "OD Jackknife Maximum",
      "set": {
        "recovery": "29+18 land"
      }
    },
    {
      "category": "normal",
      "move": "OD Jus Cool",
      "set": {
        "recovery": "36"
      }
    },
    {
      "category": "normal",
      "move": "Party in the Air",
      "set": {
        "recovery": "3 land"
      }
    },
    {
      "category": "normal",
      "move": "Stand HK",
      "set": {
        "recovery": "*22"
      }
    },
    {
      "category": "normal",
      "move": "Sunrise Heel",
      "set": {
        "startup": "19"
      }
    },
    {
      "category": "normal",
      "move": "Threebeat Combo 2",
      "set": {
        "recovery": "20",
        "startup": "9"
      }
    }
  ],
  "generatedAt": "2026-04-01T13:11:49.694614+00:00",
  "notes": [
    "Auto-generated from official SF6 frame pages and FAT comparison.",
    "Review before apply; move matching is name-based and may miss/skip ambiguous rows."
  ],
  "source": "official-streetfighter-com-frame-vs-fat",
  "sourceUrl": "https://www.streetfighter.com/6/character/deejay/frame"
}